salopylib/__init__.py
salopylib/modulo1.py
salopylib/modulo2.py
salopylib/modulo3.py
salopylib/modulo4.py
salopylib-1.4.4.dist-info/METADATA
salopylib-1.4.4.dist-info/WHEEL
salopylib-1.4.4.dist-info/top_level.txt
salopylib-1.4.4.dist-info/RECORD
