Metadata-Version: 2.1
Name: salopylib
Version: 1.4.4
Summary: Ajuste de datos con Kernels
Home-page: https://www.instagram.com/salo_mei343/
Author: Salo <3
Author-email: salome.osoriom@udea.edu.co
License: MIT
Requires-Python: >=3.11.2
Requires-Dist: numpy ==1.26.1
Requires-Dist: matplotlib ==3.8.1
Requires-Dist: pandas ==2.1.2
